youtubei/__init__.py
youtubei/_registries.py
youtubei/clients/__init__.py
youtubei/clients/android/__init__.py
youtubei/clients/android/constants.py
youtubei/clients/android/parser.py
youtubei/clients/android/responses.py
youtubei/clients/android/types.py
youtubei/clients/android/wrapper.py
youtubei/clients/ios/__init__.py
youtubei/clients/ios/constants.py
youtubei/clients/ios/parser.py
youtubei/clients/ios/responses.py
youtubei/clients/ios/types.py
youtubei/clients/ios/wrapper.py
youtubei/clients/ios_music/__init__.py
youtubei/clients/ios_music/constants.py
youtubei/clients/ios_music/parser.py
youtubei/clients/ios_music/responses.py
youtubei/clients/ios_music/wrapper.py
youtubei/clients/web/__init__.py
youtubei/clients/web/constants.py
youtubei/clients/web/parser.py
youtubei/clients/web/responses.py
youtubei/clients/web/wrapper.py
youtubei/clients/web_remix/__init__.py
youtubei/clients/web_remix/constants.py
youtubei/clients/web_remix/models.py
youtubei/clients/web_remix/parser.py
youtubei/clients/web_remix/responses.py
youtubei/clients/web_remix/types.py
youtubei/clients/web_remix/wrapper.py
youtubei/enums/__init__.py
youtubei/enums/_base.py
youtubei/enums/action.py
youtubei/enums/icon.py
youtubei/enums/music.py
youtubei/enums/other.py
youtubei/models/__init__.py
youtubei/models/_base.py
youtubei/models/accessibility.py
youtubei/models/actions.py
youtubei/models/ad.py
youtubei/models/colour.py
youtubei/models/command.py
youtubei/models/commands.py
youtubei/models/config.py
youtubei/models/contexts.py
youtubei/models/data.py
youtubei/models/data_bound.py
youtubei/models/endpoints.py
youtubei/models/logging.py
youtubei/models/metadata.py
youtubei/models/music.py
youtubei/models/other.py
youtubei/models/params.py
youtubei/models/reminders.py
youtubei/models/response.py
youtubei/models/text.py
youtubei/models/thumbnail.py
youtubei/parse/__init__.py
youtubei/parse/constants.py
youtubei/parse/exceptions.py
youtubei/parse/parser.py
youtubei/parse/registry.py
youtubei-0.1.3.dist-info/LICENSE
youtubei-0.1.3.dist-info/METADATA
youtubei-0.1.3.dist-info/WHEEL
youtubei-0.1.3.dist-info/RECORD
